db/__init__.py
db/db.py
db/mongo_db.py
db/mysql_db.py
db/redis_db.py
wb_db-0.0.5.dist-info/METADATA
wb_db-0.0.5.dist-info/WHEEL
wb_db-0.0.5.dist-info/licenses/LICENSE
wb_db-0.0.5.dist-info/RECORD
