Metadata-Version: 2.4
Name: wb-db
Version: 0.0.5
Summary: 
License-File: LICENSE
Author: mathewgeola
Author-email: mathewgeola@gmail.com
Requires-Python: >=3.12
Classifier: Programming Language :: Python :: 3
Classifier: Programming Language :: Python :: 3.12
Classifier: Programming Language :: Python :: 3.13
Classifier: Programming Language :: Python :: 3.14
Requires-Dist: cryptography (>=46.0.3,<47.0.0)
Requires-Dist: furl (>=2.1.4,<3.0.0)
Requires-Dist: openpyxl (>=3.1.5,<4.0.0)
Requires-Dist: pandas (>=2.3.3,<3.0.0)
Requires-Dist: pymongo (>=4.15.3,<5.0.0)
Requires-Dist: pymysql (>=1.1.2,<2.0.0)
Requires-Dist: redis (>=6.4.0,<7.0.0)
